frankfurter/__init__.py
frankfurter/engine.py
frankfurter/exceptions.py
frankfurter/logger.py
frankfurter/utils.py
frankfurter-2.0.0.dist-info/LICENSE
frankfurter-2.0.0.dist-info/METADATA
frankfurter-2.0.0.dist-info/WHEEL
frankfurter-2.0.0.dist-info/top_level.txt
frankfurter-2.0.0.dist-info/RECORD
