Metadata-Version: 2.1
Name: frankfurter
Version: 2.0.0
Summary: A lightweight wrapper for the frankfurter API
Home-page: https://www.frankfurter.app
Author: Pranav Chaturvedi
Author-email: pranavhfs1@gmail.com
Maintainer: PranavChaturvedi
License: MIT
Project-URL: Homepage, https://www.frankfurter.app
Project-URL: Documentation, https://github.com/PranavChaturvedi/frankfurter/blob/main/README.md
Project-URL: Repository, https://github.com/PranavChaturvedi/frankfurter
Classifier: Intended Audience :: Developers
Classifier: License :: OSI Approved :: MIT License
Classifier: Programming Language :: Python :: 3.12
Classifier: Programming Language :: Python :: 3.11
Classifier: Programming Language :: Python :: 3.10
Classifier: Programming Language :: Python :: 3.9
Classifier: Programming Language :: Python :: 3.8
Classifier: Topic :: Software Development :: Libraries :: Python Modules
Classifier: Topic :: Utilities
Requires-Python: >=3.8
License-File: LICENSE
